component_contribution/__init__.py
component_contribution/linalg.py
component_contribution/parameters.py
component_contribution/predict.py
component_contribution/preprocessor.py
component_contribution/trainer.py
component_contribution/training_data.py
component_contribution/data/__init__.py
component_contribution/data/toy_training_data.csv
component_contribution-0.6.0.dist-info/LICENSE
component_contribution-0.6.0.dist-info/METADATA
component_contribution-0.6.0.dist-info/WHEEL
component_contribution-0.6.0.dist-info/top_level.txt
component_contribution-0.6.0.dist-info/zip-safe
component_contribution-0.6.0.dist-info/RECORD
